f5tarea4primos/__init__.py
f5tarea4primos-1.0.dist-info/LICENSE
f5tarea4primos-1.0.dist-info/METADATA
f5tarea4primos-1.0.dist-info/WHEEL
f5tarea4primos-1.0.dist-info/top_level.txt
f5tarea4primos-1.0.dist-info/RECORD
